[
  {
    "version": "20",
    "name": "gcc",
    "tags": [
      "11",
      "11.3",
      "11.3.0",
      "latest",
      "bullseye",
      "11-bullseye",
      "11.3-bullseye",
      "11.3.0-bullseye"
    ],
    "images": [
      {
        "platform": {
          "os": "linux",
          "architecture": "amd64"
        },
        "sha": "b3d0691e428cf7da4a983c91a772cc5b5ee2d6b4",
        "repo": "https://github.com/docker-library/gcc.git",
        "path": "11/Dockerfile"
      },
      {
        "platform": {
          "os": "linux",
          "architecture": "arm"
        },
        "sha": "b3d0691e428cf7da4a983c91a772cc5b5ee2d6b4",
        "repo": "https://github.com/docker-library/gcc.git",
        "path": "11/Dockerfile"
      },
      {
        "platform": {
          "os": "linux",
          "architecture": "arm",
          "variant": "v7"
        },
        "sha": "b3d0691e428cf7da4a983c91a772cc5b5ee2d6b4",
        "repo": "https://github.com/docker-library/gcc.git",
        "path": "11/Dockerfile"
      },
      {
        "platform": {
          "os": "linux",
          "architecture": "arm64",
          "variant": "v8"
        },
        "sha": "b3d0691e428cf7da4a983c91a772cc5b5ee2d6b4",
        "repo": "https://github.com/docker-library/gcc.git",
        "path": "11/Dockerfile"
      },
      {
        "platform": {
          "os": "linux",
          "architecture": "ppc64le"
        },
        "sha": "b3d0691e428cf7da4a983c91a772cc5b5ee2d6b4",
        "repo": "https://github.com/docker-library/gcc.git",
        "path": "11/Dockerfile"
      },
      {
        "platform": {
          "os": "linux",
          "architecture": "s390x"
        },
        "sha": "b3d0691e428cf7da4a983c91a772cc5b5ee2d6b4",
        "repo": "https://github.com/docker-library/gcc.git",
        "path": "11/Dockerfile"
      }
    ]
  },
  {
    "version": "20",
    "name": "gcc",
    "tags": [
      "10",
      "10.3",
      "10.3.0",
      "10-buster",
      "10.3-buster",
      "10.3.0-buster"
    ],
    "images": [
      {
        "platform": {
          "os": "linux",
          "architecture": "amd64"
        },
        "sha": "a49434c14bb5fd8aa7d1d66b366195bbafea4e7e",
        "repo": "https://github.com/docker-library/gcc.git",
        "path": "10/Dockerfile"
      },
      {
        "platform": {
          "os": "linux",
          "architecture": "arm"
        },
        "sha": "a49434c14bb5fd8aa7d1d66b366195bbafea4e7e",
        "repo": "https://github.com/docker-library/gcc.git",
        "path": "10/Dockerfile"
      },
      {
        "platform": {
          "os": "linux",
          "architecture": "arm",
          "variant": "v7"
        },
        "sha": "a49434c14bb5fd8aa7d1d66b366195bbafea4e7e",
        "repo": "https://github.com/docker-library/gcc.git",
        "path": "10/Dockerfile"
      },
      {
        "platform": {
          "os": "linux",
          "architecture": "arm64",
          "variant": "v8"
        },
        "sha": "a49434c14bb5fd8aa7d1d66b366195bbafea4e7e",
        "repo": "https://github.com/docker-library/gcc.git",
        "path": "10/Dockerfile"
      },
      {
        "platform": {
          "os": "linux",
          "architecture": "ppc64le"
        },
        "sha": "a49434c14bb5fd8aa7d1d66b366195bbafea4e7e",
        "repo": "https://github.com/docker-library/gcc.git",
        "path": "10/Dockerfile"
      },
      {
        "platform": {
          "os": "linux",
          "architecture": "s390x"
        },
        "sha": "a49434c14bb5fd8aa7d1d66b366195bbafea4e7e",
        "repo": "https://github.com/docker-library/gcc.git",
        "path": "10/Dockerfile"
      }
    ]
  },
  {
    "version": "20",
    "name": "gcc",
    "tags": [
      "9",
      "9.4",
      "9.4.0",
      "9-buster",
      "9.4-buster",
      "9.4.0-buster"
    ],
    "images": [
      {
        "platform": {
          "os": "linux",
          "architecture": "amd64"
        },
        "sha": "a49434c14bb5fd8aa7d1d66b366195bbafea4e7e",
        "repo": "https://github.com/docker-library/gcc.git",
        "path": "9/Dockerfile"
      },
      {
        "platform": {
          "os": "linux",
          "architecture": "arm"
        },
        "sha": "a49434c14bb5fd8aa7d1d66b366195bbafea4e7e",
        "repo": "https://github.com/docker-library/gcc.git",
        "path": "9/Dockerfile"
      },
      {
        "platform": {
          "os": "linux",
          "architecture": "arm",
          "variant": "v7"
        },
        "sha": "a49434c14bb5fd8aa7d1d66b366195bbafea4e7e",
        "repo": "https://github.com/docker-library/gcc.git",
        "path": "9/Dockerfile"
      },
      {
        "platform": {
          "os": "linux",
          "architecture": "arm64",
          "variant": "v8"
        },
        "sha": "a49434c14bb5fd8aa7d1d66b366195bbafea4e7e",
        "repo": "https://github.com/docker-library/gcc.git",
        "path": "9/Dockerfile"
      },
      {
        "platform": {
          "os": "linux",
          "architecture": "ppc64le"
        },
        "sha": "a49434c14bb5fd8aa7d1d66b366195bbafea4e7e",
        "repo": "https://github.com/docker-library/gcc.git",
        "path": "9/Dockerfile"
      },
      {
        "platform": {
          "os": "linux",
          "architecture": "s390x"
        },
        "sha": "a49434c14bb5fd8aa7d1d66b366195bbafea4e7e",
        "repo": "https://github.com/docker-library/gcc.git",
        "path": "9/Dockerfile"
      }
    ]
  },
  {
    "version": "20",
    "name": "gcc",
    "tags": [
      "8",
      "8.5",
      "8.5.0",
      "8-buster",
      "8.5-buster",
      "8.5.0-buster"
    ],
    "images": [
      {
        "platform": {
          "os": "linux",
          "architecture": "amd64"
        },
        "sha": "a49434c14bb5fd8aa7d1d66b366195bbafea4e7e",
        "repo": "https://github.com/docker-library/gcc.git",
        "path": "8/Dockerfile"
      },
      {
        "platform": {
          "os": "linux",
          "architecture": "arm"
        },
        "sha": "a49434c14bb5fd8aa7d1d66b366195bbafea4e7e",
        "repo": "https://github.com/docker-library/gcc.git",
        "path": "8/Dockerfile"
      },
      {
        "platform": {
          "os": "linux",
          "architecture": "arm",
          "variant": "v7"
        },
        "sha": "a49434c14bb5fd8aa7d1d66b366195bbafea4e7e",
        "repo": "https://github.com/docker-library/gcc.git",
        "path": "8/Dockerfile"
      },
      {
        "platform": {
          "os": "linux",
          "architecture": "arm64",
          "variant": "v8"
        },
        "sha": "a49434c14bb5fd8aa7d1d66b366195bbafea4e7e",
        "repo": "https://github.com/docker-library/gcc.git",
        "path": "8/Dockerfile"
      },
      {
        "platform": {
          "os": "linux",
          "architecture": "ppc64le"
        },
        "sha": "a49434c14bb5fd8aa7d1d66b366195bbafea4e7e",
        "repo": "https://github.com/docker-library/gcc.git",
        "path": "8/Dockerfile"
      },
      {
        "platform": {
          "os": "linux",
          "architecture": "s390x"
        },
        "sha": "a49434c14bb5fd8aa7d1d66b366195bbafea4e7e",
        "repo": "https://github.com/docker-library/gcc.git",
        "path": "8/Dockerfile"
      }
    ]
  }
]
