[
  {
    "version": "26",
    "name": "krakend",
    "tags": [
      "2",
      "2.13",
      "2.13.6",
      "latest"
    ],
    "images": [
      {
        "platform": {
          "os": "linux",
          "architecture": "amd64"
        },
        "sha": "55a0b89b95073e736db2a1b3786eef68d0814b7e",
        "repo": "https://github.com/krakend/docker-library.git",
        "path": "2.13.6/Dockerfile"
      },
      {
        "platform": {
          "os": "linux",
          "architecture": "arm64",
          "variant": "v8"
        },
        "sha": "55a0b89b95073e736db2a1b3786eef68d0814b7e",
        "repo": "https://github.com/krakend/docker-library.git",
        "path": "2.13.6/Dockerfile"
      }
    ]
  }
]
