[
  {
    "lastModified": "2022-08-10T08:28:08.439Z",
    "name": "mysql",
    "tags": [
      "8",
      "8.0",
      "8.0.30",
      "latest",
      "oracle",
      "8-oracle",
      "8.0-oracle",
      "8.0.30-oracle"
    ],
    "images": [
      {
        "platform": {
          "os": "linux",
          "architecture": "amd64"
        },
        "sha": "8a1c1d3c30e71c8efef064e26064a195737e7e1d",
        "repo": "https://github.com/docker-library/mysql.git",
        "path": "8.0/Dockerfile.oracle"
      },
      {
        "platform": {
          "os": "linux",
          "architecture": "arm64",
          "variant": "v8"
        },
        "sha": "8a1c1d3c30e71c8efef064e26064a195737e7e1d",
        "repo": "https://github.com/docker-library/mysql.git",
        "path": "8.0/Dockerfile.oracle"
      }
    ]
  },
  {
    "lastModified": "2022-08-10T08:28:08.439Z",
    "name": "mysql",
    "tags": [
      "debian",
      "8-debian",
      "8.0-debian",
      "8.0.30-debian"
    ],
    "images": [
      {
        "platform": {
          "os": "linux",
          "architecture": "amd64"
        },
        "sha": "8a1c1d3c30e71c8efef064e26064a195737e7e1d",
        "repo": "https://github.com/docker-library/mysql.git",
        "path": "8.0/Dockerfile.debian"
      }
    ]
  },
  {
    "lastModified": "2022-08-10T08:28:08.439Z",
    "name": "mysql",
    "tags": [
      "5",
      "5.7",
      "5.7.39",
      "5-oracle",
      "5.7-oracle",
      "5.7.39-oracle"
    ],
    "images": [
      {
        "platform": {
          "os": "linux",
          "architecture": "amd64"
        },
        "sha": "eb9697a801186d440355c55e81512e0441a5a854",
        "repo": "https://github.com/docker-library/mysql.git",
        "path": "5.7/Dockerfile.oracle"
      }
    ]
  },
  {
    "lastModified": "2022-08-10T08:28:08.439Z",
    "name": "mysql",
    "tags": [
      "5-debian",
      "5.7-debian",
      "5.7.39-debian"
    ],
    "images": [
      {
        "platform": {
          "os": "linux",
          "architecture": "amd64"
        },
        "sha": "eb9697a801186d440355c55e81512e0441a5a854",
        "repo": "https://github.com/docker-library/mysql.git",
        "path": "5.7/Dockerfile.debian"
      }
    ]
  }
]
