[
  {
    "version": "26",
    "name": "photon",
    "tags": [
      "5.0",
      "latest",
      "5.0-20230508"
    ],
    "images": [
      {
        "platform": {
          "os": "linux",
          "architecture": "amd64"
        },
        "sha": "632a31370122286585265e8f90f8d01abf6b48f8",
        "repo": "https://github.com/vmware/photon-docker-image.git",
        "path": "docker/Dockerfile",
        "branch": "refs/heads/x86_64/5.0-20230508"
      },
      {
        "platform": {
          "os": "linux",
          "architecture": "arm64",
          "variant": "v8"
        },
        "sha": "3ab31c008ad4b0fcc5ce209ed0ae38acb68ae1fd",
        "repo": "https://github.com/vmware/photon-docker-image.git",
        "path": "docker/Dockerfile",
        "branch": "refs/heads/aarch64/5.0-20230508"
      }
    ]
  },
  {
    "version": "26",
    "name": "photon",
    "tags": [
      "4.0",
      "4.0-20230506"
    ],
    "images": [
      {
        "platform": {
          "os": "linux",
          "architecture": "amd64"
        },
        "sha": "4a20654b07e42375415fdf6a1c6cf863059f9bfb",
        "repo": "https://github.com/vmware/photon-docker-image.git",
        "path": "docker/Dockerfile",
        "branch": "refs/heads/x86_64/4.0-20230506"
      },
      {
        "platform": {
          "os": "linux",
          "architecture": "arm64",
          "variant": "v8"
        },
        "sha": "d4b5383e753df9564615d6d1b8bd340e1a2795c9",
        "repo": "https://github.com/vmware/photon-docker-image.git",
        "path": "docker/Dockerfile",
        "branch": "refs/heads/aarch64/4.0-20230506"
      }
    ]
  },
  {
    "version": "26",
    "name": "photon",
    "tags": [
      "3.0",
      "3.0-20230408"
    ],
    "images": [
      {
        "platform": {
          "os": "linux",
          "architecture": "amd64"
        },
        "sha": "b7616914fd9dd6584a91df971767d6e5e93de55d",
        "repo": "https://github.com/vmware/photon-docker-image.git",
        "path": "docker/Dockerfile",
        "branch": "refs/heads/x86_64/3.0-20230408"
      },
      {
        "platform": {
          "os": "linux",
          "architecture": "arm64",
          "variant": "v8"
        },
        "sha": "0ebf9b7e58c25d228d1b2e6e43477c763d98618c",
        "repo": "https://github.com/vmware/photon-docker-image.git",
        "path": "docker/Dockerfile",
        "branch": "refs/heads/aarch64/3.0-20230408"
      }
    ]
  }
]
